django_model_extra_data/__init__.py
django_model_extra_data/models.py
django_model_extra_data/contrib/__init__.py
django_model_extra_data/contrib/rest_framework/__init__.py
django_model_extra_data/contrib/rest_framework/field_mapping.py
django_model_extra_data/contrib/rest_framework/fields.py
django_model_extra_data/contrib/rest_framework/serializers.py
django_model_extra_data/forms/__init__.py
django_model_extra_data/forms/utils.py
django_model_extra_data-0.0.1.dist-info/DESCRIPTION.rst
django_model_extra_data-0.0.1.dist-info/METADATA
django_model_extra_data-0.0.1.dist-info/RECORD
django_model_extra_data-0.0.1.dist-info/WHEEL
django_model_extra_data-0.0.1.dist-info/metadata.json
django_model_extra_data-0.0.1.dist-info/top_level.txt
